Workbook

Sheet 📊 RESUMEN
B1: 🏠 CONTROL FINANCIERO DEL HOGAR
B2: Selecciona el mes y año para filtrar el resumen
B4: MES ACTUAL | D4: AÑO | E4: ← Edita estas celdas
B5: Enero | D5: 2026
B7: 💰 INGRESOS | D7: 💸 GASTOS | F7: 📈 BALANCE | H7: 🔄 RECURRENTES | J7: 🛒 DIARIOS
B8: =SUMPRODUCT(('💰 INGRESOS'!C$5:C$500=B5)*('💰 INGRESOS'!D$5:D$500=D5)*'💰 INGRESOS'!G$5:G$500) -> 0 | D8: =SUMIF('📅 RECURRENTES'!H:H,"✅",'📅 RECURRENTES'!E:E)+SUMIFS('🛒 DIARIOS'!H:H,'🛒 DIARIOS'!C:C,B5,'🛒 DIARIOS'!D:D,D5) -> 1417 | F8: =B8-D8 -> -1417 | H8: =SUMIF('📅 RECURRENTES'!H:H,"✅",'📅 RECURRENTES'!E:E) -> 1417 | J8: =SUMIFS('🛒 DIARIOS'!H:H,'🛒 DIARIOS'!C:C,B5,'🛒 DIARIOS'!D:D,D5) -> 0
B11: 📋 GASTOS POR CATEGORÍA (mes seleccionado) | H11: 💡 GUÍA RÁPIDA
B12: Categoría | C12: Recurrentes | D12: Diarios | E12: TOTAL | F12: % gasto | H12: 1️⃣ | I12: Cambia MES y AÑO (celdas azules) para filtrar
B13: 🏠 Hogar/Alquiler | D13: =SUMIFS('🛒 DIARIOS'!H:H,'🛒 DIARIOS'!C:C,B5,'🛒 DIARIOS'!D:D,D5,'🛒 DIARIOS'!F:F,"Hogar") -> 0 | E13: =C13+D13 -> 0 | F13: =IFERROR(E13/D8,0) -> 0 | H13: 2️⃣ | I13: 💰 INGRESOS → registra sueldos al inicio de mes
B14: ⚡ Suministros | D14: =SUMIFS('🛒 DIARIOS'!H:H,'🛒 DIARIOS'!C:C,B5,'🛒 DIARIOS'!D:D,D5,'🛒 DIARIOS'!F:F,"Suministros") -> 0 | E14: =C14+D14 -> 0 | F14: =IFERROR(E14/D8,0) -> 0 | H14: 3️⃣ | I14: 📅 RECURRENTES → configura gastos fijos (solo 1 vez)
B15: 🍎 Alimentación | D15: =SUMIFS('🛒 DIARIOS'!H:H,'🛒 DIARIOS'!C:C,B5,'🛒 DIARIOS'!D:D,D5,'🛒 DIARIOS'!F:F,"Alimentación") -> 0 | E15: =C15+D15 -> 0 | F15: =IFERROR(E15/D8,0) -> 0 | H15: 4️⃣ | I15: 🛒 DIARIOS → anota cada gasto del día a día
B16: 🚗 Transporte | D16: =SUMIFS('🛒 DIARIOS'!H:H,'🛒 DIARIOS'!C:C,B5,'🛒 DIARIOS'!D:D,D5,'🛒 DIARIOS'!F:F,"Transporte") -> 0 | E16: =C16+D16 -> 0 | F16: =IFERROR(E16/D8,0) -> 0 | H16: 5️⃣ | I16: Azul = dato manual | Negro = cálculo automático
B17: 🎬 Ocio/Suscripciones | C17: =SUMIFS('📅 RECURRENTES'!E:E,'📅 RECURRENTES'!D:D,"Ocio",'📅 RECURRENTES'!H:H,"✅") -> 34 | D17: =SUMIFS('🛒 DIARIOS'!H:H,'🛒 DIARIOS'!C:C,B5,'🛒 DIARIOS'!D:D,D5,'🛒 DIARIOS'!F:F,"Ocio") -> 0 | E17: =C17+D17 -> 34 | F17: =IFERROR(E17/D8,0) -> 0.023994354
B18: 🏥 Salud | C18: =SUMIFS('📅 RECURRENTES'!E:E,'📅 RECURRENTES'!D:D,"Salud",'📅 RECURRENTES'!H:H,"✅") -> 110 | D18: =SUMIFS('🛒 DIARIOS'!H:H,'🛒 DIARIOS'!C:C,B5,'🛒 DIARIOS'!D:D,D5,'🛒 DIARIOS'!F:F,"Salud") -> 0 | E18: =C18+D18 -> 110 | F18: =IFERROR(E18/D8,0) -> 0.077628793
B19: 👗 Ropa/Personal | C19: =SUMIFS('📅 RECURRENTES'!E:E,'📅 RECURRENTES'!D:D,"Ropa",'📅 RECURRENTES'!H:H,"✅") -> 0 | D19: =SUMIFS('🛒 DIARIOS'!H:H,'🛒 DIARIOS'!C:C,B5,'🛒 DIARIOS'!D:D,D5,'🛒 DIARIOS'!F:F,"Ropa") -> 0 | E19: =C19+D19 -> 0 | F19: =IFERROR(E19/D8,0) -> 0
B20: 💻 Tecnología | C20: =SUMIFS('📅 RECURRENTES'!E:E,'📅 RECURRENTES'!D:D,"Tecnología",'📅 RECURRENTES'!H:H,"✅") -> 3 | D20: =SUMIFS('🛒 DIARIOS'!H:H,'🛒 DIARIOS'!C:C,B5,'🛒 DIARIOS'!D:D,D5,'🛒 DIARIOS'!F:F,"Tecnología") -> 0 | E20: =C20+D20 -> 3 | F20: =IFERROR(E20/D8,0) -> 0.0021171489
B21: 📦 Otros | C21: =SUMIFS('📅 RECURRENTES'!E:E,'📅 RECURRENTES'!D:D,"Otros",'📅 RECURRENTES'!H:H,"✅") -> 0 | D21: =SUMIFS('🛒 DIARIOS'!H:H,'🛒 DIARIOS'!C:C,B5,'🛒 DIARIOS'!D:D,D5,'🛒 DIARIOS'!F:F,"Otros") -> 0 | E21: =C21+D21 -> 0 | F21: =IFERROR(E21/D8,0) -> 0
B22: TOTAL | C22: =SUM(C13:C21) -> 147 | D22: =SUM(D13:D21) -> 0 | E22: =SUM(E13:E21) -> 147 | F22: =100% -> 1

Sheet 💰 INGRESOS
B1: 💰 REGISTRO DE INGRESOS MENSUALES
B2: Registra aquí los ingresos de cada mes. Añade una fila por persona y concepto.
B4: # | C4: MES | D4: AÑO | E4: PERSONA | F4: CONCEPTO | G4: IMPORTE | H4: NOTAS

Sheet 📅 RECURRENTES
B1: 📅 GASTOS RECURRENTES Y FIJOS
B2: Configura aquí tus gastos fijos. Se cuentan automáticamente en el resumen cada mes.
B4: # | C4: NOMBRE DEL GASTO | D4: CATEGORÍA | E4: IMPORTE/MES | F4: DÍA COBRO | G4: FRECUENCIA | H4: ACTIVO | I4: NOTAS
B5: 1 | C5: Alquiler / Hipoteca | D5: Hogar | E5: 900 | F5: 1 | G5: Mensual | H5: ✅
B6: 2 | C6: Electricidad | D6: Suministros | E6: 80 | F6: 15 | G6: Mensual | H6: ✅ | I6: Endesa
B7: 3 | C7: Gas | D7: Suministros | E7: 50 | F7: 15 | G7: Mensual | H7: ✅ | I7: Naturgy
B8: 4 | C8: Agua | D8: Suministros | E8: 25 | F8: 20 | G8: Mensual | H8: ✅
B9: 5 | C9: Internet + Fibra | D9: Suministros | E9: 45 | F9: 5 | G9: Mensual | H9: ✅ | I9: Movistar
B10: 6 | C10: Teléfono Persona 1 | D10: Suministros | E10: 20 | F10: 5 | G10: Mensual | H10: ✅
B11: 7 | C11: Teléfono Persona 2 | D11: Suministros | E11: 20 | F11: 5 | G11: Mensual | H11: ✅
B12: 8 | C12: Netflix | D12: Ocio | E12: 18 | F12: 10 | G12: Mensual | H12: ✅
B13: 9 | C13: Spotify | D13: Ocio | E13: 11 | F13: 10 | G13: Mensual | H13: ✅
B14: 10 | C14: Amazon Prime | D14: Ocio | E14: 5 | F14: 22 | G14: Mensual | H14: ✅
B15: 11 | C15: Gimnasio Persona 1 | D15: Salud | E15: 30 | F15: 1 | G15: Mensual | H15: ✅
B16: 12 | C16: Seguro del Hogar | D16: Hogar | E16: 35 | F16: 1 | G16: Mensual | H16: ✅ | I16: 420€/año ÷ 12
B17: 13 | C17: Seguro de Coche | D17: Transporte | E17: 55 | F17: 1 | G17: Mensual | H17: ✅ | I17: 660€/año ÷ 12
B18: 14 | C18: Seguro de Salud | D18: Salud | E18: 80 | F18: 1 | G18: Mensual | H18: ✅ | I18: Sanitas
B19: 15 | C19: Comunidad de vecinos | D19: Hogar | E19: 40 | F19: 1 | G19: Mensual | H19: ✅
B20: 16 | C20: IBI (mensualizado) | D20: Hogar | E20: 25 | F20: 1 | G20: Mensual | H20: ⏸️ | I20: 350€/año ÷ 12
B21: 17 | C21: Google One / Backup | D21: Tecnología | E21: 3 | F21: 15 | G21: Mensual | H21: ✅
B44: TOTAL RECURRENTES ACTIVOS (✅): | E44: =SUMIF(H5:H500,"✅",E5:E500) -> 1417

Sheet 🛒 DIARIOS
B1: 🛒 REGISTRO DE GASTOS DIARIOS
B2: Aquí registráis cada gasto del día a día. Ambos podéis ir añadiendo filas.
B4: # | C4: MES | D4: AÑO | E4: FECHA | F4: CATEGORÍA | G4: DESCRIPCIÓN | H4: IMPORTE | I4: QUIÉN PAGA | J4: PAGADO CON | K4: NOTAS
B5: 1 | C5: Enero | D5: 2025 | E5: 01/01/2025 | F5: Alimentación | G5: Mercadona - compra semanal | H5: 85.3 | I5: Persona 1 | J5: Tarjeta
B6: 2 | C6: Enero | D6: 2025 | E6: 03/01/2025 | F6: Transporte | G6: Gasolina | H6: 50 | I6: Persona 2 | J6: Tarjeta
B7: 3 | C7: Enero | D7: 2025 | E7: 05/01/2025 | F7: Ocio | G7: Cine + cena | H7: 45 | I7: Ambos | J7: Efectivo | K7: Noche de viernes
B8: 4 | C8: Enero | D8: 2025 | E8: 07/01/2025 | F8: Alimentación | G8: Frutería | H8: 12.5 | I8: Persona 2 | J8: Efectivo
B9: 5 | C9: Enero | D9: 2025 | E9: 10/01/2025 | F9: Salud | G9: Farmacia | H9: 18.9 | I9: Persona 1 | J9: Tarjeta
B10: 6 | C10: Enero | D10: 2025 | E10: 12/01/2025 | F10: Alimentación | G10: Supermercado Lidl | H10: 63.4 | I10: Persona 1 | J10: Tarjeta
B11: 7 | C11: Enero | D11: 2025 | E11: 15/01/2025 | F11: Ropa | G11: Zara - rebajas invierno | H11: 89 | I11: Persona 2 | J11: Tarjeta
B12: 8 | C12: Enero | D12: 2025 | E12: 18/01/2025 | F12: Transporte | G12: Parking centro | H12: 8 | I12: Persona 1 | J12: Efectivo
B13: 9 | C13: Enero | D13: 2025 | E13: 25/01/2025 | F13: Alimentación | G13: Carnicería | H13: 32 | I13: Persona 1 | J13: Efectivo
B14: 10 | C14: Febrero | D14: 2025 | E14: 02/02/2025 | F14: Alimentación | G14: Mercadona | H14: 91.2 | I14: Persona 2 | J14: Tarjeta

Sheet 👥 USUARIOS
B1: 👥 USUARIOS DE LA APP
B2: Añade aquí los usuarios. La app los leerá al sincronizar.
B4: # | C4: NOMBRE | D4: ACTIVO
B5: 1 | C5: Persona 1 | D5: ✅
B6: 2 | C6: Persona 2 | D6: ✅
B8: 💡 Cambia "Persona 1" y "Persona 2" por vuestros nombres reales

Sheet 🏷️ CATEGORIAS
B1: 🏷️ CATEGORÍAS DE GASTOS
B2: Añade o edita categorías. El icono es el nombre del Material Symbol (ver nota).
B4: # | C4: NOMBRE | D4: ICONO (Material Symbol) | E4: ACTIVO
B5: 1 | C5: Alimentación | D5: restaurant | E5: ✅
B6: 2 | C6: Transporte | D6: directions_car | E6: ✅
B7: 3 | C7: Ocio | D7: movie | E7: ✅
B8: 4 | C8: Salud | D8: local_hospital | E8: ✅
B9: 5 | C9: Ropa | D9: checkroom | E9: ✅
B10: 6 | C10: Tecnología | D10: laptop | E10: ✅
B11: 7 | C11: Hogar | D11: home | E11: ✅
B12: 8 | C12: Suministros | D12: bolt | E12: ✅
B13: 9 | C13: Otros | D13: inventory_2 | E13: ✅
B15: 💡 Iconos disponibles: fonts.google.com/icons → copia el nombre en snake_case
B16: Ejemplo: "Vacaciones" → icono "beach_access" | "Mascota" → icono "pets"

Sheet 📆 ANUAL
B1: 📆 RESUMEN ANUAL CONSOLIDADO
B2: Vista de los 12 meses del año. Cambia el AÑO para filtrar.
B4: AÑO: | C4: 2025 | D4: ← Cambia este valor
B6: CONCEPTO | C6: Enero | D6: Febrero | E6: Marzo | F6: Abril | G6: Mayo | H6: Junio | I6: Julio | J6: Agosto | K6: Septiembre | L6: Octubre | M6: Noviembre | N6: Diciembre | O6: TOTAL AÑO
B7: 💰 Ingresos Persona 1 | C7: =SUMPRODUCT(('💰 INGRESOS'!C$5:C$500="Enero")*('💰 INGRESOS'!D$5:D$500=C$4)*('💰 INGRESOS'!E$5:E$500="Persona 1")*('💰 INGRESOS'!G$5:G$500)) -> 0 | D7: =SUMPRODUCT(('💰 INGRESOS'!C$5:C$500="Febrero")*('💰 INGRESOS'!D$5:D$500=C$4)*('💰 INGRESOS'!E$5:E$500="Persona 1")*('💰 INGRESOS'!G$5:G$500)) -> 0 | E7: =SUMPRODUCT(('💰 INGRESOS'!C$5:C$500="Marzo")*('💰 INGRESOS'!D$5:D$500=C$4)*('💰 INGRESOS'!E$5:E$500="Persona 1")*('💰 INGRESOS'!G$5:G$500)) -> 0 | F7: =SUMPRODUCT(('💰 INGRESOS'!C$5:C$500="Abril")*('💰 INGRESOS'!D$5:D$500=C$4)*('💰 INGRESOS'!E$5:E$500="Persona 1")*('💰 INGRESOS'!G$5:G$500)) -> 0 | G7: =SUMPRODUCT(('💰 INGRESOS'!C$5:C$500="Mayo")*('💰 INGRESOS'!D$5:D$500=C$4)*('💰 INGRESOS'!E$5:E$500="Persona 1")*('💰 INGRESOS'!G$5:G$500)) -> 0 | H7: =SUMPRODUCT(('💰 INGRESOS'!C$5:C$500="Junio")*('💰 INGRESOS'!D$5:D$500=C$4)*('💰 INGRESOS'!E$5:E$500="Persona 1")*('💰 INGRESOS'!G$5:G$500)) -> 0 | I7: =SUMPRODUCT(('💰 INGRESOS'!C$5:C$500="Julio")*('💰 INGRESOS'!D$5:D$500=C$4)*('💰 INGRESOS'!E$5:E$500="Persona 1")*('💰 INGRESOS'!G$5:G$500)) -> 0 | J7: =SUMPRODUCT(('💰 INGRESOS'!C$5:C$500="Agosto")*('💰 INGRESOS'!D$5:D$500=C$4)*('💰 INGRESOS'!E$5:E$500="Persona 1")*('💰 INGRESOS'!G$5:G$500)) -> 0 | K7: =SUMPRODUCT(('💰 INGRESOS'!C$5:C$500="Septiembre")*('💰 INGRESOS'!D$5:D$500=C$4)*('💰 INGRESOS'!E$5:E$500="Persona 1")*('💰 INGRESOS'!G$5:G$500)) -> 0 | L7: =SUMPRODUCT(('💰 INGRESOS'!C$5:C$500="Octubre")*('💰 INGRESOS'!D$5:D$500=C$4)*('💰 INGRESOS'!E$5:E$500="Persona 1")*('💰 INGRESOS'!G$5:G$500)) -> 0 | M7: =SUMPRODUCT(('💰 INGRESOS'!C$5:C$500="Noviembre")*('💰 INGRESOS'!D$5:D$500=C$4)*('💰 INGRESOS'!E$5:E$500="Persona 1")*('💰 INGRESOS'!G$5:G$500)) -> 0 | N7: =SUMPRODUCT(('💰 INGRESOS'!C$5:C$500="Diciembre")*('💰 INGRESOS'!D$5:D$500=C$4)*('💰 INGRESOS'!E$5:E$500="Persona 1")*('💰 INGRESOS'!G$5:G$500)) -> 0 | O7: =SUM(C7:N7) -> 0
B8: 💰 Ingresos Persona 2 | C8: =SUMPRODUCT(('💰 INGRESOS'!C$5:C$500="Enero")*('💰 INGRESOS'!D$5:D$500=C$4)*('💰 INGRESOS'!E$5:E$500="Persona 2")*('💰 INGRESOS'!G$5:G$500)) -> 0 | D8: =SUMPRODUCT(('💰 INGRESOS'!C$5:C$500="Febrero")*('💰 INGRESOS'!D$5:D$500=C$4)*('💰 INGRESOS'!E$5:E$500="Persona 2")*('💰 INGRESOS'!G$5:G$500)) -> 0 | E8: =SUMPRODUCT(('💰 INGRESOS'!C$5:C$500="Marzo")*('💰 INGRESOS'!D$5:D$500=C$4)*('💰 INGRESOS'!E$5:E$500="Persona 2")*('💰 INGRESOS'!G$5:G$500)) -> 0 | F8: =SUMPRODUCT(('💰 INGRESOS'!C$5:C$500="Abril")*('💰 INGRESOS'!D$5:D$500=C$4)*('💰 INGRESOS'!E$5:E$500="Persona 2")*('💰 INGRESOS'!G$5:G$500)) -> 0 | G8: =SUMPRODUCT(('💰 INGRESOS'!C$5:C$500="Mayo")*('💰 INGRESOS'!D$5:D$500=C$4)*('💰 INGRESOS'!E$5:E$500="Persona 2")*('💰 INGRESOS'!G$5:G$500)) -> 0 | H8: =SUMPRODUCT(('💰 INGRESOS'!C$5:C$500="Junio")*('💰 INGRESOS'!D$5:D$500=C$4)*('💰 INGRESOS'!E$5:E$500="Persona 2")*('💰 INGRESOS'!G$5:G$500)) -> 0 | I8: =SUMPRODUCT(('💰 INGRESOS'!C$5:C$500="Julio")*('💰 INGRESOS'!D$5:D$500=C$4)*('💰 INGRESOS'!E$5:E$500="Persona 2")*('💰 INGRESOS'!G$5:G$500)) -> 0 | J8: =SUMPRODUCT(('💰 INGRESOS'!C$5:C$500="Agosto")*('💰 INGRESOS'!D$5:D$500=C$4)*('💰 INGRESOS'!E$5:E$500="Persona 2")*('💰 INGRESOS'!G$5:G$500)) -> 0 | K8: =SUMPRODUCT(('💰 INGRESOS'!C$5:C$500="Septiembre")*('💰 INGRESOS'!D$5:D$500=C$4)*('💰 INGRESOS'!E$5:E$500="Persona 2")*('💰 INGRESOS'!G$5:G$500)) -> 0 | L8: =SUMPRODUCT(('💰 INGRESOS'!C$5:C$500="Octubre")*('💰 INGRESOS'!D$5:D$500=C$4)*('💰 INGRESOS'!E$5:E$500="Persona 2")*('💰 INGRESOS'!G$5:G$500)) -> 0 | M8: =SUMPRODUCT(('💰 INGRESOS'!C$5:C$500="Noviembre")*('💰 INGRESOS'!D$5:D$500=C$4)*('💰 INGRESOS'!E$5:E$500="Persona 2")*('💰 INGRESOS'!G$5:G$500)) -> 0 | N8: =SUMPRODUCT(('💰 INGRESOS'!C$5:C$500="Diciembre")*('💰 INGRESOS'!D$5:D$500=C$4)*('💰 INGRESOS'!E$5:E$500="Persona 2")*('💰 INGRESOS'!G$5:G$500)) -> 0 | O8: =SUM(C8:N8) -> 0
B9: 💰 TOTAL INGRESOS | C9: =SUMPRODUCT(('💰 INGRESOS'!C$5:C$500="Enero")*('💰 INGRESOS'!D$5:D$500=C$4)*('💰 INGRESOS'!G$5:G$500)) -> 0 | D9: =SUMPRODUCT(('💰 INGRESOS'!C$5:C$500="Febrero")*('💰 INGRESOS'!D$5:D$500=C$4)*('💰 INGRESOS'!G$5:G$500)) -> 0 | E9: =SUMPRODUCT(('💰 INGRESOS'!C$5:C$500="Marzo")*('💰 INGRESOS'!D$5:D$500=C$4)*('💰 INGRESOS'!G$5:G$500)) -> 0 | F9: =SUMPRODUCT(('💰 INGRESOS'!C$5:C$500="Abril")*('💰 INGRESOS'!D$5:D$500=C$4)*('💰 INGRESOS'!G$5:G$500)) -> 0 | G9: =SUMPRODUCT(('💰 INGRESOS'!C$5:C$500="Mayo")*('💰 INGRESOS'!D$5:D$500=C$4)*('💰 INGRESOS'!G$5:G$500)) -> 0 | H9: =SUMPRODUCT(('💰 INGRESOS'!C$5:C$500="Junio")*('💰 INGRESOS'!D$5:D$500=C$4)*('💰 INGRESOS'!G$5:G$500)) -> 0 | I9: =SUMPRODUCT(('💰 INGRESOS'!C$5:C$500="Julio")*('💰 INGRESOS'!D$5:D$500=C$4)*('💰 INGRESOS'!G$5:G$500)) -> 0 | J9: =SUMPRODUCT(('💰 INGRESOS'!C$5:C$500="Agosto")*('💰 INGRESOS'!D$5:D$500=C$4)*('💰 INGRESOS'!G$5:G$500)) -> 0 | K9: =SUMPRODUCT(('💰 INGRESOS'!C$5:C$500="Septiembre")*('💰 INGRESOS'!D$5:D$500=C$4)*('💰 INGRESOS'!G$5:G$500)) -> 0 | L9: =SUMPRODUCT(('💰 INGRESOS'!C$5:C$500="Octubre")*('💰 INGRESOS'!D$5:D$500=C$4)*('💰 INGRESOS'!G$5:G$500)) -> 0 | M9: =SUMPRODUCT(('💰 INGRESOS'!C$5:C$500="Noviembre")*('💰 INGRESOS'!D$5:D$500=C$4)*('💰 INGRESOS'!G$5:G$500)) -> 0 | N9: =SUMPRODUCT(('💰 INGRESOS'!C$5:C$500="Diciembre")*('💰 INGRESOS'!D$5:D$500=C$4)*('💰 INGRESOS'!G$5:G$500)) -> 0 | O9: =SUM(C9:N9) -> 0
B11: 📅 Recurrentes fijos | C11: =SUMIF('📅 RECURRENTES'!H$5:H$500,"✅",'📅 RECURRENTES'!E$5:E$500) -> 1417 | D11: =SUMIF('📅 RECURRENTES'!H$5:H$500,"✅",'📅 RECURRENTES'!E$5:E$500) -> 1417 | E11: =SUMIF('📅 RECURRENTES'!H$5:H$500,"✅",'📅 RECURRENTES'!E$5:E$500) -> 1417 | F11: =SUMIF('📅 RECURRENTES'!H$5:H$500,"✅",'📅 RECURRENTES'!E$5:E$500) -> 1417 | G11: =SUMIF('📅 RECURRENTES'!H$5:H$500,"✅",'📅 RECURRENTES'!E$5:E$500) -> 1417 | H11: =SUMIF('📅 RECURRENTES'!H$5:H$500,"✅",'📅 RECURRENTES'!E$5:E$500) -> 1417 | I11: =SUMIF('📅 RECURRENTES'!H$5:H$500,"✅",'📅 RECURRENTES'!E$5:E$500) -> 1417 | J11: =SUMIF('📅 RECURRENTES'!H$5:H$500,"✅",'📅 RECURRENTES'!E$5:E$500) -> 1417 | K11: =SUMIF('📅 RECURRENTES'!H$5:H$500,"✅",'📅 RECURRENTES'!E$5:E$500) -> 1417 | L11: =SUMIF('📅 RECURRENTES'!H$5:H$500,"✅",'📅 RECURRENTES'!E$5:E$500) -> 1417 | M11: =SUMIF('📅 RECURRENTES'!H$5:H$500,"✅",'📅 RECURRENTES'!E$5:E$500) -> 1417 | N11: =SUMIF('📅 RECURRENTES'!H$5:H$500,"✅",'📅 RECURRENTES'!E$5:E$500) -> 1417 | O11: =SUM(C11:N11) -> 17004
B12: 🛒 Gastos diarios | C12: =SUMPRODUCT(('🛒 DIARIOS'!C$5:C$500="Enero")*('🛒 DIARIOS'!D$5:D$500=C$4)*('🛒 DIARIOS'!H$5:H$500)) -> 404.1 | D12: =SUMPRODUCT(('🛒 DIARIOS'!C$5:C$500="Febrero")*('🛒 DIARIOS'!D$5:D$500=C$4)*('🛒 DIARIOS'!H$5:H$500)) -> 91.2 | E12: =SUMPRODUCT(('🛒 DIARIOS'!C$5:C$500="Marzo")*('🛒 DIARIOS'!D$5:D$500=C$4)*('🛒 DIARIOS'!H$5:H$500)) -> 0 | F12: =SUMPRODUCT(('🛒 DIARIOS'!C$5:C$500="Abril")*('🛒 DIARIOS'!D$5:D$500=C$4)*('🛒 DIARIOS'!H$5:H$500)) -> 0 | G12: =SUMPRODUCT(('🛒 DIARIOS'!C$5:C$500="Mayo")*('🛒 DIARIOS'!D$5:D$500=C$4)*('🛒 DIARIOS'!H$5:H$500)) -> 0 | H12: =SUMPRODUCT(('🛒 DIARIOS'!C$5:C$500="Junio")*('🛒 DIARIOS'!D$5:D$500=C$4)*('🛒 DIARIOS'!H$5:H$500)) -> 0 | I12: =SUMPRODUCT(('🛒 DIARIOS'!C$5:C$500="Julio")*('🛒 DIARIOS'!D$5:D$500=C$4)*('🛒 DIARIOS'!H$5:H$500)) -> 0 | J12: =SUMPRODUCT(('🛒 DIARIOS'!C$5:C$500="Agosto")*('🛒 DIARIOS'!D$5:D$500=C$4)*('🛒 DIARIOS'!H$5:H$500)) -> 0 | K12: =SUMPRODUCT(('🛒 DIARIOS'!C$5:C$500="Septiembre")*('🛒 DIARIOS'!D$5:D$500=C$4)*('🛒 DIARIOS'!H$5:H$500)) -> 0 | L12: =SUMPRODUCT(('🛒 DIARIOS'!C$5:C$500="Octubre")*('🛒 DIARIOS'!D$5:D$500=C$4)*('🛒 DIARIOS'!H$5:H$500)) -> 0 | M12: =SUMPRODUCT(('🛒 DIARIOS'!C$5:C$500="Noviembre")*('🛒 DIARIOS'!D$5:D$500=C$4)*('🛒 DIARIOS'!H$5:H$500)) -> 0 | N12: =SUMPRODUCT(('🛒 DIARIOS'!C$5:C$500="Diciembre")*('🛒 DIARIOS'!D$5:D$500=C$4)*('🛒 DIARIOS'!H$5:H$500)) -> 0 | O12: =SUM(C12:N12) -> 495.3
B13: 💸 TOTAL GASTOS | C13: =C11+C12 -> 1821.1 | D13: =D11+D12 -> 1508.2 | E13: =E11+E12 -> 1417 | F13: =F11+F12 -> 1417 | G13: =G11+G12 -> 1417 | H13: =H11+H12 -> 1417 | I13: =I11+I12 -> 1417 | J13: =J11+J12 -> 1417 | ... N13: =N11+N12 -> 1417 | O13: =SUM(C13:N13) -> 17499.3
B15: 📈 BALANCE MENSUAL | C15: =C9-C13 -> -1821.1 | D15: =D9-D13 -> -1508.2 | E15: =E9-E13 -> -1417 | F15: =F9-F13 -> -1417 | G15: =G9-G13 -> -1417 | H15: =H9-H13 -> -1417 | I15: =I9-I13 -> -1417 | J15: =J9-J13 -> -1417 | ... N15: =N9-N13 -> -1417 | O15: =SUM(C15:N15) -> -17499.3
B16: 💡 % Ahorro s/ ingresos | C16: =IFERROR((C9-C13)/C9,0) -> 0 | D16: =IFERROR((D9-D13)/D9,0) -> 0 | E16: =IFERROR((E9-E13)/E9,0) -> 0 | F16: =IFERROR((F9-F13)/F9,0) -> 0 | G16: =IFERROR((G9-G13)/G9,0) -> 0 | H16: =IFERROR((H9-H13)/H9,0) -> 0 | I16: =IFERROR((I9-I13)/I9,0) -> 0 | J16: =IFERROR((J9-J13)/J9,0) -> 0 | ... O16: =IFERROR((O9-O13)/O9,0) -> 0
